Workbook

Sheet DashBoard
B2: EDAN Sismo Cali — Dashboard Reporte 12 de Agosto 2026 - Hora 7:00 Hrs
B3: Se actualiza automáticamente al editar o agregar filas en "EDAN 100826 - Datos Madre" | H3: Casos por comuna
H4: Comuna | I4: Casos
H5: Comuna 1 | I5: =COUNTIF('EDAN 100826 - Datos Madre'!$F$2:$F$2186,"COMUNA 1") -> 9
B6: TOTAL CASOS | D6: PRIORIDAD ALTA | H6: Comuna 10 | I6: =COUNTIF('EDAN 100826 - Datos Madre'!$F$2:$F$2186,"COMUNA 10") -> 34
B7: =COUNTA('EDAN 100826 - Datos Madre'!A2:A2184) -> 863 | D7: =COUNTIF('EDAN 100826 - Datos Madre'!$B$2:$B$2186,"ALTA") -> 48 | H7: Comuna 11 | I7: =COUNTIF('EDAN 100826 - Datos Madre'!$F$2:$F$2186,"COMUNA 11") -> 5
H8: Comuna 13 | I8: =COUNTIF('EDAN 100826 - Datos Madre'!$F$2:$F$2186,"COMUNA 13") -> 4
H9: Comuna 14 | I9: =COUNTIF('EDAN 100826 - Datos Madre'!$F$2:$F$2186,"COMUNA 14") -> 4
H10: Comuna 2 | I10: =COUNTIF('EDAN 100826 - Datos Madre'!$F$2:$F$2186,"COMUNA 2") -> 118
H11: Comuna 21 | I11: =COUNTIF('EDAN 100826 - Datos Madre'!$F$2:$F$2186,"COMUNA 21") -> 5
B12: Casos por color (semáforo) | H12: Comuna 22 | I12: =COUNTIF('EDAN 100826 - Datos Madre'!$F$2:$F$2186,"COMUNA 22") -> 9
B13: Color | C13: Significado | D13: Casos | H13: Comuna 3 | I13: =COUNTIF('EDAN 100826 - Datos Madre'!$F$2:$F$2186,"COMUNA 3") -> 57
B14: Naranja | C14: En atención - Organismos de socorro | D14: =COUNTIF('EDAN 100826 - Datos Madre'!$D$2:$D$2186,"NARANJA") -> 29 | H14: Comuna 4 | I14: =COUNTIF('EDAN 100826 - Datos Madre'!$F$2:$F$2186,"COMUNA 4") -> 11
B15: Morado | C15: En validación - Profesionales Voluntarios | D15: =COUNTIF('EDAN 100826 - Datos Madre'!$D$2:$D$2186,"MORADO") -> 484 | E15: Visitados 294 | F15: En digitalización | H15: Comuna 5 | I15: =COUNTIF('EDAN 100826 - Datos Madre'!$F$2:$F$2186,"COMUNA 5") -> 22
B16: Verde | C16: Atendido | D16: =COUNTIF('EDAN 100826 - Datos Madre'!$D$2:$D$2186,"VERDE") -> 39 | H16: Comuna 6 | I16: =COUNTIF('EDAN 100826 - Datos Madre'!$F$2:$F$2186,"COMUNA 6") -> 9
B17: Amarillo | C17: En validación SGRED | D17: =COUNTIF('EDAN 100826 - Datos Madre'!$D$2:$D$2186,"AMARILLO") -> 14 | H17: Comuna 8 | I17: =COUNTIF('EDAN 100826 - Datos Madre'!$F$2:$F$2186,"COMUNA 8") -> 13
B18: Rojo | C18: Pendiente por atención organismo de socorro | D18: =COUNTIF('EDAN 100826 - Datos Madre'!$D$2:$D$2186,"ROJO") -> 6 | H18: Comuna 9 | I18: =COUNTIF('EDAN 100826 - Datos Madre'!$F$2:$F$2186,"COMUNA 9") -> 38
B19: Sin clasificar | C19: Pendiente por atención | D19: =COUNTIF('EDAN 100826 - Datos Madre'!$D$2:$D$2186,"SIN CLASIFICAR") -> 283
C20: Anulado | D20: =COUNTIF('EDAN 100826 - Datos Madre'!$D$2:$D$2186,"NEGRO") -> 8 | H20: Total | I20: =SUBTOTAL(9,I5:I18) -> 338
B23: Reporte General
C24: Colapsos | E24: Daños | F24: Atrapamientos | G24: Heridos | H24: Rescatados | I24: Fallecidos
B25: TOTALES | C25: 66 | E25: 680 | F25: 174 | G25: 1008 | H25: 88 | I25: 74
C26: Colapsos General
G27: Sujeto a datos recibidos por otras fuentes Virgilio F.
B32: Estado | C32: Colapso Total | D32: Colapso Parcial | E32: Suma
B33: Atendido | C33: =SUMPRODUCT(('EDAN 100826 - Datos Madre'!$R$2:$R$2184=1)*(TRIM('EDAN 100826 - Datos Madre'!$C$2:$C$2184)=$B33)) -> 5 | D33: =SUMPRODUCT(('EDAN 100826 - Datos Madre'!$S$2:$S$2184=1)*(TRIM('EDAN 100826 - Datos Madre'!$C$2:$C$2184)=$B33)) -> 0 | E33: =SUBTOTAL(9,C33:D33) -> 5
B34: En atención | C34: =SUMPRODUCT(('EDAN 100826 - Datos Madre'!$R$2:$R$2184=1)*(TRIM('EDAN 100826 - Datos Madre'!$C$2:$C$2184)=$B34)) -> 24 | D34: =SUMPRODUCT(('EDAN 100826 - Datos Madre'!$S$2:$S$2184=1)*(TRIM('EDAN 100826 - Datos Madre'!$C$2:$C$2184)=$B34)) -> 17 | E34: =SUBTOTAL(9,C34:D34) -> 41
B35: En validación | C35: =SUMPRODUCT(('EDAN 100826 - Datos Madre'!$R$2:$R$2184=1)*(TRIM('EDAN 100826 - Datos Madre'!$C$2:$C$2184)=$B35)) -> 2 | D35: =SUMPRODUCT(('EDAN 100826 - Datos Madre'!$S$2:$S$2184=1)*(TRIM('EDAN 100826 - Datos Madre'!$C$2:$C$2184)=$B35)) -> 0 | E35: =SUBTOTAL(9,C35:D35) -> 2
B36: Pendiente | C36: =SUMPRODUCT(('EDAN 100826 - Datos Madre'!$R$2:$R$2184=1)*(TRIM('EDAN 100826 - Datos Madre'!$C$2:$C$2184)=$B36)) -> 11 | D36: =SUMPRODUCT(('EDAN 100826 - Datos Madre'!$S$2:$S$2184=1)*(TRIM('EDAN 100826 - Datos Madre'!$C$2:$C$2184)=$B36)) -> 11 | E36: =SUBTOTAL(9,C36:D36) -> 22
B37: Validado | C37: =SUMPRODUCT(('EDAN 100826 - Datos Madre'!$R$2:$R$2184=1)*(TRIM('EDAN 100826 - Datos Madre'!$C$2:$C$2184)=$B37)) -> 0 | D37: =SUMPRODUCT(('EDAN 100826 - Datos Madre'!$S$2:$S$2184=1)*(TRIM('EDAN 100826 - Datos Madre'!$C$2:$C$2184)=$B37)) -> 0 | E37: =SUBTOTAL(9,C37:D37) -> 0
B38: ANULADO | C38: =SUMPRODUCT(('EDAN 100826 - Datos Madre'!$R$2:$R$2184=1)*(TRIM('EDAN 100826 - Datos Madre'!$C$2:$C$2184)=$B38)) -> 0 | D38: =SUMPRODUCT(('EDAN 100826 - Datos Madre'!$S$2:$S$2184=1)*(TRIM('EDAN 100826 - Datos Madre'!$C$2:$C$2184)=$B38)) -> 0 | E38: =SUBTOTAL(9,C38:D38) -> 0
B39: Total | C39: =SUBTOTAL(9,C33:C38) -> 42 | D39: =SUBTOTAL(9,D33:D38) -> 28 | E39: =E33+E34+E35+E36+E37+E38 -> 70

Sheet EDAN 100826 - Datos Madre
A1: Consecutivo | B1: Prioridad | C1: Estado | D1: Color semaforo | E1: Urgente | F1: Comuna - Corregimiento | G1: Sector | H1: Barrio | I1: Tipo | K1: Referencia | L1: Direccion completa | M1: Descripción | N1: Normalizacion | O1: Personas Evacuadas | P1: Seres sintientes | Q1: Atencion de la respuesta | R1: Colapso Total | S1: Colapso Parcial | T1: Daños | U1: Atrapamientos | V1: Rescatados | W1: Fallecidos | X1: Hospital/Clinica | Y1: NOMBRE DELEGADO | Z1: Observación Gestión del Riesgo | AA1: SOLICITUDES PENDIENTES | AB1: REFERENCIADO EN EL MAPA | AC1: DESAPARECIDOS | AD1: COORDENADAS | AE1: DESCRIPCION DE LA SITUACION | AF1: Observaciones generales (FORMULARIO)
A2: 1 | B2: ALTA | C2: Atendido | D2: NARANJA | E2: =IF(OR($B2="ALTA",AND(ISNUMBER($W2),$W2>0),AND($U2<>"",$U2<>"NO")),"SI","") -> SI | F2: Comuna 19 | G2: Sur | H2: El Lido | I2: Edificio | J2: Carrera 44 con calle 5 | L2: =CONCATENATE(J2,", ",H2,", Cali") -> Carrera 44 con calle 5, El Lido, Cali | M2: Colapso de 3 edificaciones y 4 en riesgo de colapso | N2: Colapso Estructural | Q2: BROS - DCC | R2: 1 | U2: SI | V2: 7 | W2: 3 | Y2: DANIELA GONZALEZ/MAFE | Z2: En atención se requiere busqueda tecnica. (Bros).. Se asistio con 5 Recursos (máquinas y vehículo de comando), en horas de la noche nos retiramos. El área queda LIMPIA | AA2: Actualización BROS
A3: =A2+1 -> 2 | B3: BAJO | C3: En atención | D3: MORADO | E3: =IF(OR($B3="ALTA",AND(ISNUMBER($W3),$W3>0),AND($U3<>"",$U3<>"NO")),"SI","") | F3: Comuna 17 | G3: Sur | H3: La Hacienda | I3: Edificio | J3: Carrera 72 con calle 11 | L3: =CONCATENATE(J3,", ",H3,", Cali") -> Carrera 72 con calle 11, La Hacienda, Cali | M3: Colapso Estructural | N3: Colapso Estructural | Q3: PROFESIONAL VOLUNTARIO | R3: 1 | U3: NO | Z3: (Bros)...ver punto Nro 20 | AA3: Actualización BROS
A4: =A3+1 -> 3 | B4: BAJO | C4: Visitado | D4: MORADO | E4: =IF(OR($B4="ALTA",AND(ISNUMBER($W4),$W4>0),AND($U4<>"",$U4<>"NO")),"SI","") | F4: Comuna 17 | G4: Sur | H4: Limonar | I4: Edificio | J4: Calle 10 Bis # 70 34 | L4: =CONCATENATE(J4,", ",H4,", Cali") -> Calle 10 Bis # 70 34, Limonar, Cali | M4: Colapso Estructural | N4: Colapso Estructural | Q4: PROFESIONAL VOLUNTARIO | R4: 1 | U4: NO | Z4: (Bros)...ver punto Nro 20 | AA4: Actualización BROS | AD4: 3.3935084, -76.5436393 | AE4: Se encuentra el inmueble en su mayoría con buen estado, parte de la fachada que mira hacia la autopista sur-oriental presenta desprendimiento de elementos no estructurales. Dentro de las zonas comunes se hayan fisuras leves en elementos no estructurales. El bloque b de la unidad presenta daños en las columnas laterales de primer piso, dejando a la vista el acero de refuerzo y dejando una inclinación evidente a simple vista en el muro continuo.
A5: =A4+1 -> 4 | B5: - | C5: ANULADO | D5: NEGRO | E5: - | F5: - | G5: - | H5: - | I5: - | J5: - | K5: - | L5: - | M5: - | N5: - | O5: - | P5: - | Q5: - | R5: - | S5: - | T5: - | U5: - | V5: - | W5: - | X5: - | Y5: - | Z5: - | AA5: - | AB5: -
A6: =A5+1 -> 5 | B6: ALTA | C6: En atención | D6: NARANJA | E6: =IF(OR($B6="ALTA",AND(ISNUMBER($W6),$W6>0),AND($U6<>"",$U6<>"NO")),"SI","") -> SI | F6: Comuna 19 | G6: Sur | H6: Cuarto de Legua | I6: Edificio | J6: Carrera 57 # 3-88 | K6: Edificio Ana del Pilar | L6: =CONCATENATE(J6,", ",H6,", Cali") -> Carrera 57 # 3-88, Cuarto de Legua, Cali | M6: Colapso estructural | N6: Colapso Estructural | Q6: BROS | R6: 1 | U6: SI | V6: 10 | W6: 7 | Z6: Reporte enseguida del D1, no hay personal de bomberos, no hay energía, se necesitan linternas y guantes. (Bros)... Nos encontramos trabajando con varios recursos (aproximadamente 10 vehículos, Bomberos Yumbo) siendo las 23: 20 horas se continua las labores, el área va desde la calle 3 con carrera 50 a la carrera 56. El número de rescatados y fallecidos corresponde al secto indicado. | AA6: Actualización BROS | AB6: DIGITALIZADO
A7: =A6+1 -> 6 | B7: - | C7: ANULADO | D7: NEGRO | E7: - | F7: - | G7: - | H7: - | I7: - | J7: - | K7: - | L7: - | M7: - | N7: - | O7: - | P7: - | Q7: - | R7: - | T7: - | U7: - | V7: - | W7: - | X7: - | Y7: - | Z7: - | AA7: - | AB7: -
A8: =A7+1 -> 7 | B8: ALTA | C8: En atención | D8: NARANJA | E8: =IF(OR($B8="ALTA",AND(ISNUMBER($W8),$W8>0),AND($U8<>"",$U8<>"NO")),"SI","") -> SI | F8: Comuna 19 | G8: Sur | H8: Pampalinda | I8: Edificio | J8: Calle 3 # 61B | K8: Edificio de 3 Pisos | L8: =CONCATENATE(J8,", ",H8,", Cali") -> Calle 3 # 61B, Pampalinda, Cali | M8: Colapso Estructural | N8: Colapso Estructural | Q8: DCC - BROS | R8: 1 | U8: SI | Z8: En atención, salimos la estación alameda en la máquina B2 a la Carrera 61 # 3-167 cuarto de Legua | AA8: Actualización BROS
A9: =A8+1 -> 8 | B9: ALTA | C9: Atendido | D9: VERDE | E9: =IF(OR($B9="ALTA",AND(ISNUMBER($W9),$W9>0),AND($U9<>"",$U9<>"NO")),"SI","") -> SI | F9: Comuna 19 | G9: Sur | H9: Los Cámbulos | I9: Edificio | J9: Av. Roosevelt (Calle 6) con Carrera 42 | L9: =CONCATENATE(J9,", ",H9,", Cali") -> Av. Roosevelt (Calle 6) con Carrera 42, Los Cámbulos, Cali | M9: Daño estructural | N9: Afectación estructural | O9: SI | Q9: BROS | T9: 1 | U9: NO | V9: 5 | Z9: Edificio averiado, se rescata una feminina del sexto piso, lugar acordonado y se da indicacaciones de no habilitar el lugar. (Bros)... = igual información
A10: =A9+1 -> 9 | B10: ALTA | C10: En atención | D10: NARANJA | E10: =IF(OR($B10="ALTA",AND(ISNUMBER($W10),$W10>0),AND($U10<>"",$U10<>"NO")),"SI","") -> SI | F10: Comuna 9 | G10: Sur | H10: Olimpico | I10: Edificio | J10: Carrera 38a # 10 | K10: Edificio Punto Rojo | L10: =CONCATENATE(J10,", ",H10,", Cali") -> Carrera 38a # 10, Olimpico, Cali | M10: Colapso estructural | N10: Colapso Estructural | Q10: RIESGOS - BROS | R10: 1 | U10: 2 | V10: 6 | Y10: Juan Manuel Montaño y Jose Luis Cobo | Z10: Se requiere personal personas atrapadas. (Bros)... Se asitio con dos recursos. ZONA LIMPIA | AA10: Actualización BROS | AB10: Por favor actualizar BOMBEROS - OK DIGITALIZADO
A11: =A10+1 -> 10 | B11: BAJO | C11: Atendido | D11: VERDE | E11: =IF(OR($B11="ALTA",AND(ISNUMBER($W11),$W11>0),AND($U11<>"",$U11<>"NO")),"SI","") | F11: Comuna 19 | G11: Sur | H11: San Fernando | I11: Edificio | J11: Carrera 36 con Calle 5 B2 69 | L11: =CONCATENATE(J11,", ",H11,", Cali") -> Carrera 36 con Calle 5 B2 69, San Fernando, Cali | M11: Daño estructural | N11: Afectación estructural | Q11: RIESGOS | T11: 1 | U11: NO | Y11: Gebel Taba | Z11: Riesgos - Vivienda de dos niveles afectada en fachada. Fractura en paredes de habitación de la parte frontal. Maria Eugenia Ospina.,
A12: =A11+1 -> 11 | B12: ALTA | C12: En atención | D12: AMARILLO | E12: =IF(OR($B12="ALTA",AND(ISNUMBER($W12),$W12>0),AND($U12<>"",$U12<>"NO")),"SI","") -> SI | F12: Comuna 19 | G12: Sur | H12: Cuarto de Legua | I12: Casa | J12: Carrera 58 # 3-138 | L12: =CONCATENATE(J12,", ",H12,", Cali") -> Carrera 58 # 3-138, Cuarto de Legua, Cali | M12: Colapso estructural | N12: Colapso Estructural | Q12: BROS | R12: 1 | U12: 5 | Z12: Familia de 5 personas atrapada - no hay equipos de rescate. (Bros)... Ver punto Nro 6 | AA12: Actualización BROS
A13: =A12+1 -> 12 | B13: BAJO | C13: Atendido | D13: VERDE | E13: =IF(OR($B13="ALTA",AND(ISNUMBER($W13),$W13>0),AND($U13<>"",$U13<>"NO")),"SI","") | F13: Comuna 9 | G13: Centro | H13: Junin | I13: Edificio | J13: Autopista Sur # 13-01 | K13: Hotel La Luna | L13: =CONCATENATE(J13,", ",H13,", Cali") -> Autopista Sur # 13-01, Junin, Cali | M13: Colapso estructural | N13: Colapso Estructural | Q13: CRC | R13: 1 | U13: NO | Y13: Giovanny Ordoñez y Felipe Galves | Z13: Se cayo el hotel la luna, no hay personas atrapadas. (Bros)... No hubo intervención por parte de Bomberos
A14: =A13+1 -> 13 | B14: MEDIO | C14: Pendiente | D14: ROJO | E14: =IF(OR($B14="ALTA",AND(ISNUMBER($W14),$W14>0),AND($U14<>"",$U14<>"NO")),"SI","") | F14: Comuna 19 | G14: Sur | H14: Urbanización Tequendama | I14: Parroquia | J14: Calle 5 con Carrera 42 | K14: Parroquia La Ascensión del Señor | L14: =CONCATENATE(J14,", ",H14,", Cali") -> Calle 5 con Carrera 42, Urbanización Tequendama, Cali | M14: Colapso estructural | N14: Colapso Estructural | R14: 1 | U14: NO | Z14: Se requiere validar, no hubo atención de bomberos. Fuga de gas y maquinaria para buscar 3 víctimas con movilidad reducida Calle 5ta 42 esquina 3235906044 Oscar Aristizábal | AA14: Actualización BROS
A15: =A14+1 -> 14 | B15: ALTA | C15: En atención | D15: NARANJA | E15: =IF(OR($B15="ALTA",AND(ISNUMBER($W15),$W15>0),AND($U15<>"",$U15<>"NO")),"SI","") -> SI | F15: Comuna 5 | G15: Norte | H15: Chiminangos II | I15: Edificio | J15: Calle 62B # 1A9-365 | K15: Torre G | L15: =CONCATENATE(J15,", ",H15,", Cali") -> Calle 62B # 1A9-365, Chiminangos II, Cali | M15: Colapso estructural | N15: Colapso Estructural | Q15: CRC | R15: 1 | T15: 1 | U15: 20 | V15: 3 | Y15: Miguel Medina | Z15: En atención - Priorizado USAR Nacional, Se recomendó evacuación | AA15: Actualización BROS
A16: =A15+1 -> 15 | B16: ALTA | C16: En atención | D16: NARANJA | E16: =IF(OR($B16="ALTA",AND(ISNUMBER($W16),$W16>0),AND($U16<>"",$U16<>"NO")),"SI","") -> SI | F16: Comuna 19 | G16: Sur | H16: Tequendama | I16: Edificio | J16: Carrera 42 con calle 5 | K16: Quintapan | L16: =CONCATENATE(J16,", ",H16,", Cali") -> Carrera 42 con calle 5, Tequendama, Cali | M16: Colapso estructural | N16: Colapso Estructural | Q16: DCC - BROS | R16: 1 | U16: 20 | Z16: Se encuentan en labores de rescate, se requiere apoyo de Seguridad y Justicia; policia con el fin de controlar la aglomeración de personas. | AA16: Actualización BROS | AB16: Por favor actualizar BOMBEROS - OK DIGITALIZADO
A17: =A16+1 -> 16 | B17: ALTA | C17: En atención | D17: NARANJA | E17: =IF(OR($B17="ALTA",AND(ISNUMBER($W17),$W17>0),AND($U17<>"",$U17<>"NO")),"SI","") -> SI | F17: Comuna 19 | G17: Sur | H17: El Refugio | I17: Edificio | J17: Carrera 67 # 3c -15 | K17: Barrio el refugio | L17: =CONCATENATE(J17,", ",H17,", Cali") -> Carrera 67 # 3c -15, El Refugio, Cali | M17: Colapso estructural | N17: Colapso Estructural | Q17: BROS - RIESGOS | R17: 1 | U17: 2 | V17: 4 | W17: 3 | Y17: YESICA JORDAN | Z17: 1. descripcion de la afectación: Edifico de 5 pisos más azotea colapso, 2. se tienen sobrevivientes ya se sacó 1, se necesita urgente personal para ayudar a sacar parece que hay más sobrevivientes, 3. Tienen 2 máquinas de bomberos, 4. Nos indica que ya cruz roja está en este punto, 20 personas están bajo los escombros, 5. Dos torres están evacuadas por posible colapso. (Bros)... Siendo las 23:50 horas continua bomberos trabajando en el sector | AA17: Actualización BROS
A18: =A17+1 -> 17 | B18: - | C18: ANULADO | D18: NARANJA | E18: - | F18: - | G18: - | H18: - | I18: - | J18: - | K18: - | L18: - | M18: - | N18: - | O18: - | P18: - | Q18: - | R18: - | T18: - | U18: - | V18: - | W18: - | X18: - | Y18: - | Z18: - | AA18: - | AB18: -
A19: =A18+1 -> 18 | B19: BAJO | C19: Atendido | D19: VERDE | E19: =IF(OR($B19="ALTA",AND(ISNUMBER($W19),$W19>0),AND($U19<>"",$U19<>"NO")),"SI","") -> SI | F19: Comuna 19 | G19: Oriente | H19: Poblado ll | I19: Hospital | J19: Calle 72U # 28E-00, Poblado II | K19: Hospital Carlos Holmes Trujillo | L19: =CONCATENATE(J19,", ",H19,", Cali") -> Calle 72U # 28E-00, Poblado II, Poblado ll, Cali | M19: Daño estructural | N19: Afectación estructural | Q19: Bomberos - Cruz Ruja | T19: 1 | U19: 12 | X19: 1 | Z19: Atendido - Sin atrapamientos
A20: =A19+1 -> 19 | B20: ALTA | C20: Atendido | D20: VERDE | E20: =IF(OR($B20="ALTA",AND(ISNUMBER($W20),$W20>0),AND($U20<>"",$U20<>"NO")),"SI","") -> SI | F20: Comuna 9 | G20: Centro | H20: San Bosco | I20: Casa | J20: Calle 9 con Carrera 18 | K20: N/A | L20: =CONCATENATE(J20,", ",H20,", Cali") -> Calle 9 con Carrera 18, San Bosco, Cali | M20: Daño estructural | N20: Afectación estructural | O20: SI | Q20: RIESGOS | T20: 1 | U20: NO | V20: 4 | Y20: Alejandro Barrera Daiha Navarro | Z20: Colapso de paredes dos personas sanas, paredes fracturados.
A21: =A20+1 -> 20 | B21: ALTA | C21: Atendido | D21: VERDE | E21: =IF(OR($B21="ALTA",AND(ISNUMBER($W21),$W21>0),AND($U21<>"",$U21<>"NO")),"SI","") -> SI | F21: Comuna 19 | G21: Sur | H21: Tequendama | I21: Casa | J21: Carrera 40 # 4B-26 | K21: N/A | L21: =CONCATENATE(J21,", ",H21,", Cali") -> Carrera 40 # 4B-26, Tequendama, Cali | M21: Daño estructural | N21: Afectación estructural | Q21: BROS | T21: 1 | U21: Validar | V21: 10 | W21: 1 | Z21: 10 edificios afectados. (Bros)... Se asistio con dos recursos. ZONA LIMPIA
A22: =A21+1 -> 21 | B22: - | C22: ANULADO | D22: NARANJA | E22: - | F22: - | G22: - | H22: - | I22: - | J22: - | K22: - | L22: - | M22: - | N22: - | O22: - | P22: - | Q22: - | R22: - | T22: - | U22: - | V22: - | W22: - | X22: - | Y22: - | Z22: - | AA22: - | AB22: -
A23: =A22+1 -> 22 | B23: ALTA | C23: En atención | D23: NARANJA | E23: =IF(OR($B23="ALTA",AND(ISNUMBER($W23),$W23>0),AND($U23<>"",$U23<>"NO")),"SI","") -> SI | F23: Comuna 19 | G23: Sur | H23: Eucarístico | I23: Casa | J23: Calle 10 38 21 | K23: Molino Rojo | L23: =CONCATENATE(J23,", ",H23,", Cali") -> Calle 10 38 21, Eucarístico, Cali | M23: Colapso estructural | N23: Colapso Estructural | Q23: DCC - BROS - MOVIIDAD - POLICIA | R23: 1 | U23: 2 | V23: 8 | Z23: En atención. (Bros)...Se asitio con dos recursos. ZONA LIMPIA | AA23: Actualización BROS
A24: =A23+1 -> 23 | B24: BAJO | C24: Atendido | D24: VERDE | E24: =IF(OR($B24="ALTA",AND(ISNUMBER($W24),$W24>0),AND($U24<>"",$U24<>"NO")),"SI","") -> SI | F24: Comuna 19 | G24: Sur | H24: El Lido | I24: Casa | J24: Carrera 52 # 3 20 | K24: Bodega de reciclaje | L24: =CONCATENATE(J24,", ",H24,", Cali") -> Carrera 52 # 3 20, El Lido, Cali | M24: Colapso estructural | N24: Colapso Estructural | O24: SI | Q24: BROS | R24: 1 | U24: NO | W24: 2 | Z24: Atendido, sin personas atrapadas
A25: =A24+1 -> 24 | B25: ALTA | C25: Pendiente | D25: SIN CLASIFICAR | E25: =IF(OR($B25="ALTA",AND(ISNUMBER($W25),$W25>0),AND($U25<>"",$U25<>"NO")),"SI","") -> SI | F25: Comuna 19 | G25: Sur | H25: Eucarístico | I25: Casa | J25: Carrera 38A # 6 38 | K25: N/A | L25: =CONCATENATE(J25,", ",H25,", Cali") -> Carrera 38A # 6 38, Eucarístico, Cali | M25: Daño estructural | N25: Afectación estructural | T25: 1 | Z25: Se requiere validar
A26: =A25+1 -> 25 | B26: ALTA | C26: Pendiente | D26: SIN CLASIFICAR | E26: =IF(OR($B26="ALTA",AND(ISNUMBER($W26),$W26>0),AND($U26<>"",$U26<>"NO")),"SI","") -> SI | F26: Comuna 3 | G26: Centro | H26: Centro | I26: Edificio | J26: Carrera 5 # 13 46 | K26: Edificio el cafe | L26: =CONCATENATE(J26,", ",H26,", Cali") -> Carrera 5 # 13 46, Centro, Cali | M26: Daño estructural | N26: Afectación estructural | T26: 1 | Z26: Se requiere validar
A27: =A26+1 -> 26 | B27: MEDIO | C27: Pendiente | D27: SIN CLASIFICAR | E27: =IF(OR($B27="ALTA",AND(ISNUMBER($W27),$W27>0),AND($U27<>"",$U27<>"NO")),"SI","") | F27: Comuna 19 | G27: Sur | H27: Cuarto de Legua | I27: Casa | J27: CRE 52 # 2-01 | K27: Coliseo Pueblo | L27: =CONCATENATE(J27,", ",H27,", Cali") -> CRE 52 # 2-01, Cuarto de Legua, Cali | M27: Daño estructural | N27: Afectación estructural | T27: 1 | Z27: Se requiere validar
A28: =A27+1 -> 27 | B28: ALTA | C28: En atención | D28: NARANJA | E28: =IF(OR($B28="ALTA",AND(ISNUMBER($W28),$W28>0),AND($U28<>"",$U28<>"NO")),"SI","") -> SI | F28: Comuna 19 | G28: Sur | H28: Los Cámbulos | I28: Colegio | J28: Carrera 44 con Calle 9 35 | K28: Colegio Adventista | L28: =CONCATENATE(J28,", ",H28,", Cali") -> Carrera 44 con Calle 9 35, Los Cámbulos, Cali | M28: Colapso estructural - Edificación de 8 pisos colapsada, aproximadamente 28 personas atrapadas. Fuga de gas, Edificio de 7 pisos | N28: Colapso Estructural | Q28: GAS - DCC - BROS PROFESIONAL VOLUNTARIO | R28: 1 | U28: 29 (niños) | W28: 2 | Y28: NATHALIE GARCIA - EVELIN COLLAZOS - ERON CISNEROS - MARIA ISABEL | Z28: PUNTO CRITICO En atención - asistio ICBF Equipo psicosicial y unidades moviles. (Bros)...siendo las 01:00 horas del día 11 de agosto continuamos con las labores | AA28: Actualización BROS
A29: =A28+1 -> 28 | B29: ALTA | C29: En atención | D29: NARANJA | E29: =IF(OR($B29="ALTA",AND(ISNUMBER($W29),$W29>0),AND($U29<>"",$U29<>"NO")),"SI","") -> SI | F29: Comuna 17 | G29: Sur | H29: El Limonar | I29: Edificio | J29: Carrera 72 # 10 Bis-21 | K29: Edificio Torres del Limonar | L29: =CONCATENATE(J29,", ",H29,", Cali") -> Carrera 72 # 10 Bis-21, El Limonar, Cali | M29: Colapso estructural - Niña atrapada | N29: Colapso Estructural | Q29: BROS - CRC | R29: 1 | U29: 11 | V29: 7 | Y29: DANIELA CARDONA | Z29: PUNTO CRITICO En atención - COL 19, se encuentra BOMBEROS BOGOTÁ. (Bros)...ver punto Nro 20 | AA29: Actualización BROS
A30: =A29+1 -> 29 | B30: ALTA | C30: Pendiente | D30: SIN CLASIFICAR | E30: =IF(OR($B30="ALTA",AND(ISNUMBER($W30),$W30>0),AND($U30<>"",$U30<>"NO")),"SI","") -> SI | F30: Comuna 19 | G30: Sur | H30: Tequendama | I30: Casa | J30: Calle 5E # 40 - 36 | L30: =CONCATENATE(J30,", ",H30,", Cali") -> Calle 5E # 40 - 36, Tequendama, Cali | M30: Daño estructural | N30: Afectación estructural | Q30: RIESGOS | T30: 1 | U30: Validar | Y30: CAMILA LOZANO MIGUEL LOPEZ | Z30: En validación
A31: =A30+1 -> 30 | B31: - | C31: ANULADO | D31: VERDE | E31: - | F31: - | G31: - | H31: - | I31: - | J31: - | K31: - | L31: - | M31: - | N31: - | O31: - | P31: - | Q31: - | R31: - | T31: - | U31: - | V31: - | W31: - | X31: - | Y31: - | Z31: - | AA31: - | AB31: -
A32: =A31+1 -> 31 | B32: BAJO | C32: En atención | D32: MORADO | E32: =IF(OR($B32="ALTA",AND(ISNUMBER($W32),$W32>0),AND($U32<>"",$U32<>"NO")),"SI","") | F32: Comuna 3 | G32: Centro | H32: San Pedro | I32: Tipo | J32: Calle 14 #5-20 | K32: Centro comercial la fortuna | L32: =CONCATENATE(J32,", ",H32,", Cali") -> Calle 14 #5-20, San Pedro, Cali | M32: Daño estructural | N32: Afectación estructural | O32: SI | Q32: PROFESIONAL VOLUNTARIO | T32: 1
A33: =A32+1 -> 32 | B33: MEDIO | C33: En atención | D33: NARANJA | E33: =IF(OR($B33="ALTA",AND(ISNUMBER($W33),$W33>0),AND($U33<>"",$U33<>"NO")),"SI","") | F33: comuna 9 | G33: Centro | H33: Alameda | I33: Edificio | J33: Calle 9 con carrera 22 | L33: =CONCATENATE(J33,", ",H33,", Cali") -> Calle 9 con carrera 22, Alameda, Cali | M33: Daño estructural | N33: Afectación estructural | O33: SI | Q33: BROS | T33: 1 | V33: 3 | Z33: En atención | AA33: Actualización BROS
A34: =A33+1 -> 33 | B34: BAJO | C34: En atención | D34: MORADO | E34: =IF(OR($B34="ALTA",AND(ISNUMBER($W34),$W34>0),AND($U34<>"",$U34<>"NO")),"SI","") | F34: Comuna 5 | G34: Norte | H34: Torres de Comfandi | I34: Edificio | J34: Calle 62 carrera 1b | L34: =CONCATENATE(J34,", ",H34,", Cali") -> Calle 62 carrera 1b, Torres de Comfandi, Cali | M34: Daño estructural | N34: Afectación estructural | Q34: PROFESIONAL VOLUNTARIO | T34: 1
A35: =A34+1 -> 34 | B35: BAJO | C35: En atención | D35: MORADO | E35: =IF(OR($B35="ALTA",AND(ISNUMBER($W35),$W35>0),AND($U35<>"",$U35<>"NO")),"SI","") | F35: Comuna 3 | G35: Centro | H35: San Pedro | I35: Parroquia | J35: Calle 9 #5-59 | K35: Iglesia san fracisco | L35: =CONCATENATE(J35,", ",H35,", Cali") -> Calle 9 #5-59, San Pedro, Cali | M35: Daño estructural | N35: Afectación estructural | Q35: PROFESIONAL VOLUNTARIO | T35: 1
A36: =A35+1 -> 35 | B36: BAJO | C36: En atención | D36: MORADO | E36: =IF(OR($B36="ALTA",AND(ISNUMBER($W36),$W36>0),AND($U36<>"",$U36<>"NO")),"SI","") | F36: Comuna 3 | G36: Centro | H36: San Bosco | I36: Edificio | J36: carrera 10 calle 5 | L36: =CONCATENATE(J36,", ",H36,", Cali") -> carrera 10 calle 5, San Bosco, Cali | M36: Daño estructural | N36: Afectación estructural | Q36: PROFESIONAL VOLUNTARIO | T36: 1
A37: =A36+1 -> 36 | B37: BAJO | C37: En atención | D37: MORADO | E37: =IF(OR($B37="ALTA",AND(ISNUMBER($W37),$W37>0),AND($U37<>"",$U37<>"NO")),"SI","") -> SI | F37: Comuna 5 | G37: Norte | H37: Chiminangos II | I37: Edificio | J37: Calle 62B # 1A-2-50 | K37: Sector 3 – Chiminangos | L37: =CONCATENATE(J37,", ",H37,", Cali") -> Calle 62B # 1A-2-50, Chiminangos II, Cali | M37: Daño estructural | N37: Afectación estructural | Q37: PROFESIONAL VOLUNTARIO | T37: 1 | U37: 2 | W37: 1 | Z37: Pendiente reporte fallecido
A38: =A37+1 -> 37 | B38: BAJO | C38: En atención | D38: MORADO | E38: =IF(OR($B38="ALTA",AND(ISNUMBER($W38),$W38>0),AND($U38<>"",$U38<>"NO")),"SI","") | F38: Comuna 10 | G38: Sur | H38: Colseguros | I38: Clinica | J38: Calle 10 #33-51 | K38: Clínica Nuestra Señora del Rosario | L38: =CONCATENATE(J38,", ",H38,", Cali") -> Calle 10 #33-51, Colseguros, Cali | M38: Daño estructural | N38: Alto Riesgo de Colapso | O38: SI | Q38: RIESGOS / PROFESIONAL VOLUNTARIO | T38: 1 | X38: 1 | Z38: Evacuación completa, en alto riesgo de colapso Se recmendó evacuación
A39: =A38+1 -> 38 | B39: BAJO | C39: En atención | D39: MORADO | E39: =IF(OR($B39="ALTA",AND(ISNUMBER($W39),$W39>0),AND($U39<>"",$U39<>"NO")),"SI","") -> SI | F39: Comuna 5 | G39: Norte | H39: Barranquilla | I39: Edificio | J39: carrera 1 bis con calle 59 | L39: =CONCATENATE(J39,", ",H39,", Cali") -> carrera 1 bis con calle 59, Barranquilla, Cali | M39: Daño estructural | N39: Afectación estructural | Q39: PROFESIONAL VOLUNTARIO | T39: 1 | W39: 1 | Y39: Juan David Lopez | Z39: Se requiere evacuacion 910 verde
A40: =A39+1 -> 39 | B40: BAJO | C40: En atención | D40: MORADO | E40: =IF(OR($B40="ALTA",AND(ISNUMBER($W40),$W40>0),AND($U40<>"",$U40<>"NO")),"SI","") | F40: Comuna 19 | G40: Sur | H40: Nuevo Tequendama | I40: Edificio | J40: Calle 5 e 46 82 conunto 4 apto 302 b | K40: Torres de santiagp de cali | L40: =CONCATENATE(J40,", ",H40,", Cali") -> Calle 5 e 46 82 conunto 4 apto 302 b, Nuevo Tequendama, Cali | M40: Daño estructural | N40: Afectación estructural | Q40: PROFESIONAL VOLUNTARIO | T40: 1
A41: =A40+1 -> 40 | B41: BAJO | C41: En atención | D41: NARANJA | E41: =IF(OR($B41="ALTA",AND(ISNUMBER($W41),$W41>0),AND($U41<>"",$U41<>"NO")),"SI","") | F41: Comuna 19 | G41: Sur | H41: El Refugio | I41: Edificio | J41: carrera 68 con calle 3b 61 | L41: =CONCATENATE(J41,", ",H41,", Cali") -> carrera 68 con calle 3b 61, El Refugio, Cali | M41: Daño estructural | N41: Afectación estructural | Q41: CRC | T41: 1 | Z41: En atención
A42: =A41+1 -> 41 | B42: BAJO | C42: En atención | D42: MORADO | E42: =IF(OR($B42="ALTA",AND(ISNUMBER($W42),$W42>0),AND($U42<>"",$U42<>"NO")),"SI","") | F42: Comuna 19 | G42: Sur | H42: San Fernando | I42: Edificio | J42: CR 36 5- 21-20 | L42: =CONCATENATE(J42,", ",H42,", Cali") -> CR 36 5- 21-20, San Fernando, Cali | M42: Daño estructural, evacuación controlada | N42: Afectación estructural | Q42: PROFESIONAL VOLUNTARIO | T42: 1
A43: =A42+1 -> 42 | B43: BAJO | C43: En atención | D43: MORADO | E43: =IF(OR($B43="ALTA",AND(ISNUMBER($W43),$W43>0),AND($U43<>"",$U43<>"NO")),"SI","") | F43: Comuna 3 | G43: Centro | H43: San Bosco | I43: Edificio | J43: Calle 5 con 13 y 14 | K43: C.C. La Fortuna | L43: =CONCATENATE(J43,", ",H43,", Cali") -> Calle 5 con 13 y 14, San Bosco, Cali | M43: Daño estructural, evacuación controlada | N43: Afectación estructural | Q43: PROFESIONAL VOLUNTARIO | T43: 1
A44: =A43+1 -> 43 | B44: ALTA | C44: En atención | D44: NARANJA | E44: =IF(OR($B44="ALTA",AND(ISNUMBER($W44),$W44>0),AND($U44<>"",$U44<>"NO")),"SI","") -> SI | F44: Comuna 19 | G44: Sur | H44: Tequendama | I44: Edificio | J44: Cra. 41 & Av. Roosevelt Zona: Sur | L44: =CONCATENATE(J44,", ",H44,", Cali") -> Cra. 41 & Av. Roosevelt Zona: Sur, Tequendama, Cali | M44: Colapso Estructural | N44: Colapso Estructural | O44: SI | Q44: BROS | R44: 1 | Z44: Colapsado completo, en revisión si hay personas atrapadas. | AA44: Actualización BROS
A45: =A44+1 -> 44 | B45: BAJO | C45: Atendido | D45: VERDE | E45: =IF(OR($B45="ALTA",AND(ISNUMBER($W45),$W45>0),AND($U45<>"",$U45<>"NO")),"SI","") | F45: Comuna 19 | G45: Sur | H45: Los Cámbulos | I45: Casa | J45: Calle 7 con Carrera 41 | L45: =CONCATENATE(J45,", ",H45,", Cali") -> Calle 7 con Carrera 41, Los Cámbulos, Cali | M45: Daño estructural | N45: Afectación estructural | Q45: BROS | T45: 1 | Z45: (Bros)... Se asitio al sitio. ZONA LIMPIA
A46: =A45+1 -> 45 | B46: BAJO | C46: En atención | D46: MORADO | E46: =IF(OR($B46="ALTA",AND(ISNUMBER($W46),$W46>0),AND($U46<>"",$U46<>"NO")),"SI","") | F46: Comuna 2 | G46: Norte | H46: San Vicente | I46: Clinica | J46: Av. 4 Norte #21N-54 | K46: Clínica Al Alba | L46: =CONCATENATE(J46,", ",H46,", Cali") -> Av. 4 Norte #21N-54, San Vicente, Cali | M46: Daño estructural, evacuación controlada | N46: Afectación estructural | Q46: PROFESIONAL VOLUNTARIO | T46: 1 | X46: 1 | Y46: Juan David Lopez
A47: =A46+1 -> 46 | B47: BAJO | C47: En atención | D47: MORADO | E47: =IF(OR($B47="ALTA",AND(ISNUMBER($W47),$W47>0),AND($U47<>"",$U47<>"NO")),"SI","") | F47: Comuna 19 | G47: Sur | H47: El templete | I47: Clinica | J47: Carrera 34 #7-00 | K47: Clinica Rey David | L47: =CONCATENATE(J47,", ",H47,", Cali") -> Carrera 34 #7-00, El templete, Cali | M47: Daño estructural, evacuación controlada | N47: Afectación estructural | Q47: PROFESIONAL VOLUNTARIO | T47: 1 | X47: 1 | Z47: se puede operar sin problema (helena)
A48: =A47+1 -> 47 | B48: BAJO | C48: En atención | D48: MORADO | E48: =IF(OR($B48="ALTA",AND(ISNUMBER($W48),$W48>0),AND($U48<>"",$U48<>"NO")),"SI","") | F48: Comuna 19 | G48: Sur | H48: Tequendama | I48: Clinica | J48: Calle 5E #43A-34 | K48: Clinica Sanitas | L48: =CONCATENATE(J48,", ",H48,", Cali") -> Calle 5E #43A-34, Tequendama, Cali | M48: Daño estructural, evacuación controlada | N48: Afectación estructural | Q48: PROFESIONAL VOLUNTARIO | T48: 1 | X48: 1
A49: =A48+1 -> 48 | B49: BAJO | C49: En atención | D49: MORADO | E49: =IF(OR($B49="ALTA",AND(ISNUMBER($W49),$W49>0),AND($U49<>"",$U49<>"NO")),"SI","") | F49: Comuna 4 | G49: Norte | H49: Bueno Madrid | I49: Clinica | J49: Av. 3 Norte #32AN-40 | K49: Clinica Cali | L49: =CONCATENATE(J49,", ",H49,", Cali") -> Av. 3 Norte #32AN-40, Bueno Madrid, Cali | M49: Daño estructural, evacuación controlada | N49: Afectación estructural | Q49: PROFESIONAL VOLUNTARIO | T49: 1 | X49: 1 | Y49: Juan David Lopez
A50: =A49+1 -> 49 | B50: BAJO | C50: En atención | D50: MORADO | E50: =IF(OR($B50="ALTA",AND(ISNUMBER($W50),$W50>0),AND($U50<>"",$U50<>"NO")),"SI","") | F50: Comuna 2 | G50: Norte | H50: Asturias | I50: Casa | J50: Calle 5N # 60 65 | K50: Asturias | L50: =CONCATENATE(J50,", ",H50,", Cali") -> Calle 5N # 60 65, Asturias, Cali | M50: Daño estructural, evacuación controlada | N50: Afectación estructural | Q50: PROFESIONAL VOLUNTARIO | T50: 1
A51: =A50+1 -> 50 | B51: BAJO | C51: En atención | D51: MORADO | E51: =IF(OR($B51="ALTA",AND(ISNUMBER($W51),$W51>0),AND($U51<>"",$U51<>"NO")),"SI","") | F51: Comuna 17 | G51: Sur | H51: San Miguel | I51: Ancianato | J51: Carrera 80 con Calle 5 | K51: Ancianato San Miguel | L51: =CONCATENATE(J51,", ",H51,", Cali") -> Carrera 80 con Calle 5, San Miguel, Cali | M51: Daño estructural, evacuación controlada | N51: Afectación estructural | Q51: PROFESIONAL VOLUNTARIO | T51: 1
A52: =A51+1 -> 51 | B52: - | C52: ANULADO | D52: VERDE | E52: - | F52: - | G52: - | H52: - | I52: - | J52: - | K52: - | L52: - | M52: - | N52: - | O52: - | P52: - | Q52: - | R52: - | T52: - | U52: - | V52: - | W52: - | X52: - | Y52: - | Z52: - | AA52: - | AB52: -
A53: =A52+1 -> 52 | B53: BAJO | C53: En atención | D53: MORADO | E53: =IF(OR($B53="ALTA",AND(ISNUMBER($W53),$W53>0),AND($U53<>"",$U53<>"NO")),"SI","") | F53: Comuna 19 | G53: Sur | H53: El Refugio | I53: Edificio | J53: Calle 3C # 63A-44 | K53: Bosques de Puente Palma | L53: =CONCATENATE(J53,", ",H53,", Cali") -> Calle 3C # 63A-44, El Refugio, Cali | M53: Daño estructural, evacuación controlada | N53: Afectación estructural | Q53: PROFESIONAL VOLUNTARIO | T53: 1
A54: =A53+1 -> 53 | B54: BAJO | C54: En atención | D54: MORADO | E54: =IF(OR($B54="ALTA",AND(ISNUMBER($W54),$W54>0),AND($U54<>"",$U54<>"NO")),"SI","") | F54: Comuna 19 | G54: Sur | H54: Tequendama | I54: Casa | J54: Calle 5E # 46 82 | L54: =CONCATENATE(J54,", ",H54,", Cali") -> Calle 5E # 46 82, Tequendama, Cali | M54: Daño estructural, evacuación controlada | N54: Afectación estructural | Q54: PROFESIONAL VOLUNTARIO | T54: 1
A55: =A54+1 -> 54 | B55: ALTA | C55: Atendido | D55: VERDE | E55: =IF(OR($B55="ALTA",AND(ISNUMBER($W55),$W55>0),AND($U55<>"",$U55<>"NO")),"SI","") -> SI | F55: Comuna 19 | G55: Sur | H55: Pampalinda | I55: Casa | J55: Calle 5 con Carrera 57 | L55: =CONCATENATE(J55,", ",H55,", Cali") -> Calle 5 con Carrera 57, Pampalinda, Cali | M55: Daño estructural | N55: Afectación estructural | O55: SI | Q55: BROS PALMIRA | T55: 1 | Z55: Riesgos - Se evidencian daños en fachadas de mampostería y elementos estructurales comprometidos, grietas que superan 5 mm horizontales verticales y diagonales.
A56: =A55+1 -> 55 | B56: BAJO | C56: En atención | D56: MORADO | E56: =IF(OR($B56="ALTA",AND(ISNUMBER($W56),$W56>0),AND($U56<>"",$U56<>"NO")),"SI","") | F56: Comuna 17 | G56: Sur | H56: Valle del Lili | I56: Edificio | J56: Calle 1B Oeste con Carrera 100 | K56: Unidad Residencial Manigua | L56: =CONCATENATE(J56,", ",H56,", Cali") -> Calle 1B Oeste con Carrera 100, Valle del Lili, Cali | M56: Daño estructural, evacuación controlada | N56: Afectación estructural | Q56: PROFESIONAL VOLUNTARIO | T56: 1
A57: =A56+1 -> 56 | B57: ALTA | C57: Atendido | D57: MORADO | E57: =IF(OR($B57="ALTA",AND(ISNUMBER($W57),$W57>0),AND($U57<>"",$U57<>"NO")),"SI","") -> SI | F57: Comuna 18 | G57: Sur | H57: Altos de Santa Elena / Polvorines | I57: Edificio | J57: Calle 1D Oeste # 100 Bis-49 | K57: Edificio Altos de Santa Elena, Etapa I | L57: =CONCATENATE(J57,", ",H57,", Cali") -> Calle 1D Oeste # 100 Bis-49, Altos de Santa Elena / Polvorines, Cali | M57: Daño estructural, evacuación controlada | N57: Alto Riesgo de Colapso | O57: SI | Q57: PROFESIONAL VOLUNTARIO | T57: 1 | Z57: Toda la Torre 85 presenta grietas externas e internas, los 20 Apartamento NO están APTOS PARA HABITAR, PUEDE PRESENTARSE UN COLAPSO, los pisos 1 y últimos se encuentran totalmente o 100% destrozados. Por instrucciones de la Señora Andrea de la Alcaldia, se nos prohíbio por temas de seguridad entrar a las viviendas, ya que se evidenciaba su peligro..
A58: =A57+1 -> 57 | B58: BAJO | C58: En atención | D58: MORADO | E58: =IF(OR($B58="ALTA",AND(ISNUMBER($W58),$W58>0),AND($U58<>"",$U58<>"NO")),"SI","") | F58: Comuna 2 | G58: Norte | H58: La Flora | I58: Edificio | J58: Avenida 7N # 56-120 | K58: Edificio Santorini–Mikonos | L58: =CONCATENATE(J58,", ",H58,", Cali") -> Avenida 7N # 56-120, La Flora, Cali | M58: Daño estructural, evacuación controlada | N58: Afectación estructural | Q58: PROFESIONAL VOLUNTARIO | T58: 1
A59: =A58+1 -> 58 | B59: BAJO | C59: En atención | D59: MORADO | E59: =IF(OR($B59="ALTA",AND(ISNUMBER($W59),$W59>0),AND($U59<>"",$U59<>"NO")),"SI","") | F59: Comuna 19 | G59: Sur | H59: Los Cámbulos | I59: Casa | J59: Calle 9 con Carrera 45 | L59: =CONCATENATE(J59,", ",H59,", Cali") -> Calle 9 con Carrera 45, Los Cámbulos, Cali | M59: Daño estructural, evacuación controlada | N59: Afectación estructural | Q59: PROFESIONAL VOLUNTARIO | T59: 1
A60: =A59+1 -> 59 | B60: BAJO | C60: Atendido | D60: VERDE | E60: =IF(OR($B60="ALTA",AND(ISNUMBER($W60),$W60>0),AND($U60<>"",$U60<>"NO")),"SI","") -> SI | F60: Comuna 10 | G60: Sur | H60: Colseguros | I60: Edificio | J60: Calle 12B # 33 45 | K60: Unidad Torres de Buganvilias | L60: =CONCATENATE(J60,", ",H60,", Cali") -> Calle 12B # 33 45, Colseguros, Cali | M60: Daño estructural | N60: Afectación estructural | O60: SI | Q60: PROFESIONAL VOLUNTARIO | T60: 1 | U60: 0 | V60: 0 | W60: 0 | X60: 0 | Y60: Nicolás Alarcón Brochero | Z60: Estructura está sin afectación, elementos de mampostería divisorios y de fachada totalmente afectados, muros de fachada caídos, se declara inhabitable por riesgo de colapso de muros de mampostería y elementos de fachada
A61: =A60+1 -> 60 | B61: ALTA | C61: En atención | D61: NARANJA | E61: =IF(OR($B61="ALTA",AND(ISNUMBER($W61),$W61>0),AND($U61<>"",$U61<>"NO")),"SI","") -> SI | F61: Comuna 19 | G61: Sur | H61: Los Cámbulos | I61: Edificio | J61: Calle 9 con Carrera 44 | K61: Edificio Vanessa | L61: =CONCATENATE(J61,", ",H61,", Cali") -> Calle 9 con Carrera 44, Los Cámbulos, Cali | M61: Daño estructural, evacuación controlada | N61: Afectación estructural | Q61: DCC - BROS | T61: 1 | U61: SI | Z61: En atención - Reporte de personas atratapadas, 1 canino fallecido - Bomberos Cali
A62: =A61+1 -> 61 | B62: BAJO | C62: Atendido | D62: VERDE | E62: =IF(OR($B62="ALTA",AND(ISNUMBER($W62),$W62>0),AND($U62<>"",$U62<>"NO")),"SI","") | F62: Comuna 19 | G62: Sur | H62: San Fernando Nuevo | I62: Ancianato | J62: Calle 5B4 #36B-45 | K62: Hogar Héroes de Vida y Amor | L62: =CONCATENATE(J62,", ",H62,", Cali") -> Calle 5B4 #36B-45, San Fernando Nuevo, Cali | M62: Daño estructural, evacuación controlada | N62: Afectación estructural | Q62: RIESGOS | T62: 1 | U62: No | Y62: Miguel Medina | Z62: Riesgos - Se requiere EDAN, grietas en paredes estructurales, No hay personas afectadas.
A63: =A62+1 -> 62 | B63: BAJO | C63: En atención | D63: MORADO | E63: =IF(OR($B63="ALTA",AND(ISNUMBER($W63),$W63>0),AND($U63<>"",$U63<>"NO")),"SI","") | F63: Comuna 3 | G63: Centro | H63: San Pedro | I63: Casa | J63: Calle 8 con Carrera 8 | L63: =CONCATENATE(J63,", ",H63,", Cali") -> Calle 8 con Carrera 8, San Pedro, Cali | M63: Daño estructural, evacuación controlada | N63: Afectación estructural | Q63: PROFESIONAL VOLUNTARIO | T63: 1
A64: =A63+1 -> 63 | B64: BAJO | C64: En atención | D64: MORADO | E64: =IF(OR($B64="ALTA",AND(ISNUMBER($W64),$W64>0),AND($U64<>"",$U64<>"NO")),"SI","") | F64: Comuna 17 | G64: Sur | H64: El Limonar | I64: Edificio | J64: Carrera 63 # 2A 3 | L64: =CONCATENATE(J64,", ",H64,", Cali") -> Carrera 63 # 2A 3, El Limonar, Cali | M64: Daño estructural, evacuación controlada | N64: Afectación estructural | Q64: PROFESIONAL VOLUNTARIO | T64: 1
A65: =A64+1 -> 64 | B65: ALTA | C65: En validación | D65: AMARILLO | E65: =IF(OR($B65="ALTA",AND(ISNUMBER($W65),$W65>0),AND($U65<>"",$U65<>"NO")),"SI","") -> SI | F65: Comuna 17 | G65: Sur | H65: Bosques del Limonar | I65: Edificio | J65: Carrera 66 # 13B 29 | L65: =CONCATENATE(J65,", ",H65,", Cali") -> Carrera 66 # 13B 29, Bosques del Limonar, Cali | M65: Daño estructural, evacuación controlada | N65: Afectación estructural | Q65: RIESGOS | T65: 1 | Y65: JOSE APOLINAR | Z65: 60 apartamentos afectados
A66: =A65+1 -> 65 | B66: BAJO | C66: En atención | D66: MORADO | E66: =IF(OR($B66="ALTA",AND(ISNUMBER($W66),$W66>0),AND($U66<>"",$U66<>"NO")),"SI","") | F66: Comuna 2 | G66: Norte | H66: La Flora | I66: Edificio | J66: Calle 41 Norte # 4N-170 | K66: EDIFICIO ALMINAR | L66: =CONCATENATE(J66,", ",H66,", Cali") -> Calle 41 Norte # 4N-170, La Flora, Cali | M66: Daño estructural, evacuación controlada | N66: Afectación estructural | Q66: PROFESIONAL VOLUNTARIO | T66: 1 | Z66: Juan Pablo Dominguez 3053365053 / Fachada muy agrietada y ladrillos cayendose
A67: =A66+1 -> 66 | B67: BAJO | C67: En atención | D67: MORADO | E67: =IF(OR($B67="ALTA",AND(ISNUMBER($W67),$W67>0),AND($U67<>"",$U67<>"NO")),"SI","") | F67: Comuna 19 | G67: Sur | H67: Nuevo Tequendama | I67: Edificio | J67: Carrera 46 calle 8 b | L67: =CONCATENATE(J67,", ",H67,", Cali") -> Carrera 46 calle 8 b, Nuevo Tequendama, Cali | M67: Daño estructural, evacuación controlada | N67: Afectación estructural | Q67: PROFESIONAL VOLUNTARIO | T67: 1
A68: =A67+1 -> 67 | B68: BAJO | C68: En atención | D68: MORADO | E68: =IF(OR($B68="ALTA",AND(ISNUMBER($W68),$W68>0),AND($U68<>"",$U68<>"NO")),"SI","") | F68: comuna 9 | G68: Centro | H68: Alameda | I68: Edificio | J68: Carrera 23 # 9 06 | L68: =CONCATENATE(J68,", ",H68,", Cali") -> Carrera 23 # 9 06, Alameda, Cali | M68: Daño estructural, evacuación controlada | N68: Afectación estructural | Q68: PROFESIONAL VOLUNTARIO | T68: 1 | U68: NO | Z68: Pendiente validar Riesgos
A69: =A68+1 -> 68 | B69: BAJO | C69: En atención | D69: MORADO | E69: =IF(OR($B69="ALTA",AND(ISNUMBER($W69),$W69>0),AND($U69<>"",$U69<>"NO")),"SI","") | F69: Comuna 19 | G69: Sur | H69: El refugio | I69: Casa | J69: Carrera 65 # 2b -14 | L69: =CONCATENATE(J69,", ",H69,", Cali") -> Carrera 65 # 2b -14, El refugio, Cali | M69: Daño estructural, evacuación controlada | N69: Afectación estructural | Q69: PROFESIONAL VOLUNTARIO | T69: 1 | Y69: Sebastian Penagos y David Arboleda
A70: =A69+1 -> 69 | B70: BAJO | C70: Atendido | D70: VERDE | E70: =IF(OR($B70="ALTA",AND(ISNUMBER($W70),$W70>0),AND($U70<>"",$U70<>"NO")),"SI","") | F70: Comuna 19 | G70: Sur | H70: San Fernando | I70: Edificio | J70: Calle 5B2 # 31 98 | L70: =CONCATENATE(J70,", ",H70,", Cali") -> Calle 5B2 # 31 98, San Fernando, Cali | M70: Daño estructural, evacuación controlada | N70: Alto Riesgo de Colapso | Q70: RIESGOS | T70: 1 | Y70: Sergio Arias | Z70: Edificio de 5 pisos en alto riesgo de colapso, pésimo estado. (Bros)...Se despacha recurso a verificar. solo daños de fachadas. ZONA LIMPIA
A71: =A70+1 -> 70 | B71: - | C71: ANULADO | D71: NARANJA | E71: - | F71: - | G71: - | H71: - | I71: - | J71: - | K71: - | L71: - | M71: - | N71: - | O71: - | P71: - | Q71: - | R71: - | T71: - | U71: - | V71: - | W71: - | X71: - | Y71: - | Z71: - | AA71: - | AB71: -
A72: =A71+1 -> 71 | B72: BAJO | C72: Atendido | D72: VERDE | E72: =IF(OR($B72="ALTA",AND(ISNUMBER($W72),$W72>0),AND($U72<>"",$U72<>"NO")),"SI","") | F72: Comuna 3 | G72: Centro | H72: San Pedro | I72: Edificio | J72: Calle 3 con Carrera 4 | L72: =CONCATENATE(J72,", ",H72,", Cali") -> Calle 3 con Carrera 4, San Pedro, Cali | M72: Daño estructural, evacuación controlada | N72: Afectación estructural | O72: SI | Q72: RIESGOS | T72: 1 | Z72: Caidas de fachadas sin victimas
A73: =A72+1 -> 72 | B73: ALTA | C73: En atención | D73: NARANJA | E73: =IF(OR($B73="ALTA",AND(ISNUMBER($W73),$W73>0),AND($U73<>"",$U73<>"NO")),"SI","") -> SI | F73: Comuna 19 | G73: Sur | H73: El Refugio | I73: Casa | J73: Carrera 67 con calle 3 C | L73: =CONCATENATE(J73,", ",H73,", Cali") -> Carrera 67 con calle 3 C, El Refugio, Cali | M73: Daño estructural, evacuación controlada | N73: Afectación estructural | Q73: BROS | T73: 1 | U73: 3 | Z73: En atención - dos edificios se cayeron de la unidad que es de 4
A74: =A73+1 -> 73 | B74: BAJO | C74: En atención | D74: MORADO | E74: =IF(OR($B74="ALTA",AND(ISNUMBER($W74),$W74>0),AND($U74<>"",$U74<>"NO")),"SI","") | F74: Comuna 19 | G74: Sur | H74: Cámbulos | I74: Clinica | J74: Cra. 46 #9C-85 | K74: Clinica Colombia | L74: =CONCATENATE(J74,", ",H74,", Cali") -> Cra. 46 #9C-85, Cámbulos, Cali | M74: Daño estructural, evacuación controlada | N74: Afectación estructural | Q74: PROFESIONAL VOLUNTARIO | T74: 1 | X74: 1
A75: =A74+1 -> 74 | B75: BAJO | C75: En atención | D75: MORADO | E75: =IF(OR($B75="ALTA",AND(ISNUMBER($W75),$W75>0),AND($U75<>"",$U75<>"NO")),"SI","") | F75: Comuna 2 | G75: Norte | H75: Versalles | I75: Clinica | J75: Av. 5A Norte #23N-46/57 | K75: Clinica Versalles | L75: =CONCATENATE(J75,", ",H75,", Cali") -> Av. 5A Norte #23N-46/57, Versalles, Cali | M75: Daño estructural, evacuación controlada | N75: Afectación estructural | Q75: PROFESIONAL VOLUNTARIO | T75: 1 | X75: 1
A76: =A75+1 -> 75 | B76: BAJO | C76: Atendido | D76: VERDE | E76: =IF(OR($B76="ALTA",AND(ISNUMBER($W76),$W76>0),AND($U76<>"",$U76<>"NO")),"SI","") -> SI | F76: Comuna 19 | G76: Sur | H76: San Fernando | I76: Hospital | J76: Calle 5 # 36-08 | K76: Hospital Universitario del Valle (HUV) | L76: =CONCATENATE(J76,", ",H76,", Cali") -> Calle 5 # 36-08, San Fernando, Cali | M76: Daño estructural, evacuación controlada | N76: Afectación estructural | O76: SI | Q76: BRS - CRC | T76: 1 | W76: 1 | X76: 1 | Y76: JUAN HERNANDEZ | Z76: Reporte: 11 de agosto - 9:11pm - Héctor Asdrúbal: se reporta q a las 6pm de hoy envió un msj a un familiar de q está bajo los escombros. - se estiman q hay 8 personas aún bajo los escombros. No se sabe si vivas. Se necesita URGENTE : Al menos 2 sierra sable. Envío referencia. Cuchillas de repuesto. | AA76: 11/08 11:28PM RESCATE - 2 Sierra sable
A77: =A76+1 -> 76 | B77: ALTA | C77: En atención | D77: NARANJA | E77: =IF(OR($B77="ALTA",AND(ISNUMBER($W77),$W77>0),AND($U77<>"",$U77<>"NO")),"SI","") -> SI | F77: Comuna 19 | G77: Sur | H77: Pampalinda | I77: Casa | J77: Carrera 62 # 2A 197 | L77: =CONCATENATE(J77,", ",H77,", Cali") -> Carrera 62 # 2A 197, Pampalinda, Cali | M77: Edificio en alto riesgo de colapso | N77: Alto Riesgo de Colapso | Q77: BROS | T77: 1 | U77: SI | Y77: 1 | Z77: Reporte de personas atratapadas, pendiente validar
A78: =A77+1 -> 77 | B78: BAJO | C78: En atención | D78: NARANJA | E78: =IF(OR($B78="ALTA",AND(ISNUMBER($W78),$W78>0),AND($U78<>"",$U78<>"NO")),"SI","") | F78: Comuna 2 | G78: Norte | H78: La Flora | I78: Edificio | J78: 3 c norte con Calle 63 | L78: =CONCATENATE(J78,", ",H78,", Cali") -> 3 c norte con Calle 63, La Flora, Cali | M78: Daño estructural, evacuación controlada | N78: Afectación estructural | Q78: DCC | T78: 1 | Z78: En atención
A79: =A78+1 -> 78 | B79: BAJO | C79: En atención | D79: NARANJA | E79: =IF(OR($B79="ALTA",AND(ISNUMBER($W79),$W79>0),AND($U79<>"",$U79<>"NO")),"SI","") | F79: Comuna 2 | G79: Norte | H79: La Flora | I79: Edificio | J79: Avenida 3 Norte 59 125 | L79: =CONCATENATE(J79,", ",H79,", Cali") -> Avenida 3 Norte 59 125, La Flora, Cali | M79: Daño estructural, evacuación controlada | N79: Afectación estructural | Q79: DCC | T79: 1 | Z79: Carros evacuados en la calle
A80: =A79+1 -> 79 | B80: BAJO | C80: En atención | D80: MORADO | E80: =IF(OR($B80="ALTA",AND(ISNUMBER($W80),$W80>0),AND($U80<>"",$U80<>"NO")),"SI","") | F80: Comuna 10 | G80: Sur | H80: Cristóbal Colón | I80: Clinica | J80: Calle 15 # 33-71 | K80: IPS CRISTOBAL COLON | L80: =CONCATENATE(J80,", ",H80,", Cali") -> Calle 15 # 33-71, Cristóbal Colón, Cali | M80: Daño estructural, evacuación controlada | N80: Afectación estructural | Q80: PROFESIONAL VOLUNTARIO | T80: 1 | X80: 1
A81: =A80+1 -> 80 | B81: BAJO | C81: En atención | D81: MORADO | E81: =IF(OR($B81="ALTA",AND(ISNUMBER($W81),$W81>0),AND($U81<>"",$U81<>"NO")),"SI","") | F81: Comuna 19 | G81: Sur | H81: Tequendama | I81: Clinica | J81: Calle 5D # 38A-35 | K81: Clinica de Colores | L81: =CONCATENATE(J81,", ",H81,", Cali") -> Calle 5D # 38A-35, Tequendama, Cali | M81: Daño estructural, evacuación controlada | N81: Afectación estructural | Q81: PROFESIONAL VOLUNTARIO | T81: 1 | X81: 1
A82: =A81+1 -> 81 | B82: BAJO | C82: En atención | D82: MORADO | E82: =IF(OR($B82="ALTA",AND(ISNUMBER($W82),$W82>0),AND($U82<>"",$U82<>"NO")),"SI","") -> SI | F82: Comuna 4 | G82: Norte | H82: Esmeralda | I82: Edificio | J82: Carrera 5C con 43 | L82: =CONCATENATE(J82,", ",H82,", Cali") -> Carrera 5C con 43, Esmeralda, Cali | M82: Fallecido Masculino - Vía Pública | N82: Levantamiento de cuerpo | Q82: PROFESIONAL VOLUNTARIO | W82: 1
A83: =A82+1 -> 82 | B83: - | C83: ANULADO | D83: VERDE | E83: - | F83: - | G83: - | H83: - | I83: - | J83: - | K83: - | L83: - | M83: - | N83: - | O83: - | P83: - | Q83: - | R83: - | T83: - | U83: - | V83: - | W83: - | X83: - | Y83: - | Z83: - | AA83: - | AB83: -
A84: =A83+1 -> 83 | B84: MEDIO | C84: Atendido | D84: VERDE | E84: =IF(OR($B84="ALTA",AND(ISNUMBER($W84),$W84>0),AND($U84<>"",$U84<>"NO")),"SI","") | F84: Comuna 19 | G84: Sur | H84: San Fernando | I84: Edificio | J84: Carrera 37 # 5b1 - 37 | K84: Edificio Liliana | L84: =CONCATENATE(J84,", ",H84,", Cali") -> Carrera 37 # 5b1 - 37, San Fernando, Cali | M84: Colapso estructural | N84: Colapso estructural | O84: SI | R84: 1 | Z84: Edificio de 4 pisos con colapso total 10 apartamentos
A85: =A84+1 -> 84 | B85: MEDIO | C85: En validación | D85: AMARILLO | E85: =IF(OR($B85="ALTA",AND(ISNUMBER($W85),$W85>0),AND($U85<>"",$U85<>"NO")),"SI","") | F85: Comuna 22 | G85: Sur | H85: Las Vegas | I85: Edificio | J85: calle 2a # 78b-30 | K85: Conjunto familiar atabanza | L85: =CONCATENATE(J85,", ",H85,", Cali") -> calle 2a # 78b-30, Las Vegas, Cali | M85: Daño estructural | N85: Afectación estructural | O85: SI | Q85: RIESGOS | T85: 1 | Y85: Carlos Rua
A86: =A85+1 -> 85 | B86: BAJO | C86: En atención | D86: MORADO | E86: =IF(OR($B86="ALTA",AND(ISNUMBER($W86),$W86>0),AND($U86<>"",$U86<>"NO")),"SI","") | F86: Comuna 2 | G86: Norte | H86: San vicente | I86: Clinica | J86: calle 19Norte con Avenida 4 Norte | K86: IPS Salud total | L86: =CONCATENATE(J86,", ",H86,", Cali") -> calle 19Norte con Avenida 4 Norte, San vicente, Cali | M86: Daño estructural, evacuación controlada | N86: Afectación estructural | Q86: PROFESIONAL VOLUNTARIO | T86: 1 | X86: 1
A87: =A86+1 -> 86 | B87: BAJO | C87: Atendido | D87: VERDE | E87: =IF(OR($B87="ALTA",AND(ISNUMBER($W87),$W87>0),AND($U87<>"",$U87<>"NO")),"SI","") | F87: Comuna 19 | G87: Sur | H87: Pampalinda | I87: Edificio | J87: carrera 59 #1e -43 | K87: Las Violetas , pampalinda, | L87: =CONCATENATE(J87,", ",H87,", Cali") -> carrera 59 #1e -43, Pampalinda, Cali | M87: Daño estructural | N87: Afectación estructural | O87: SI | Q87: SCOUT | T87: 1 | Y87: Juan Jose Mendez Scout - natalia Diaz | Z87: Edificio con columnas afectadas en el interior - desplazamineto de paredes de 5 cm . techo del 4 piso colaspso por caida de pared del edificio elder calle 1f #56-206 viven 6 familias solo se queda 1 alli
A88: =A87+1 -> 87 | B88: BAJO | C88: Atendido | D88: VERDE | E88: =IF(OR($B88="ALTA",AND(ISNUMBER($W88),$W88>0),AND($U88<>"",$U88<>"NO")),"SI","") | F88: Comuna 19 | G88: Sur | H88: San Fernando | I88: Edificio | J88: Calle 5b1 con carrera 36b | L88: =CONCATENATE(J88,", ",H88,", Cali") -> Calle 5b1 con carrera 36b, San Fernando, Cali | M88: Daño estructural, evacuación controlada | N88: Afectación estructural | Q88: RIESGOS | T88: 1 | Y88: Felipe Ortiz Rubiano | Z88: Edificio evacuado, se encuentra en alto riesgo de colapso.
A89: =A88+1 -> 88 | B89: - | C89: ANULADO | D89: VERDE | E89: - | F89: - | G89: - | H89: - | I89: - | J89: - | K89: - | L89: - | M89: - | N89: - | O89: - | P89: - | Q89: - | R89: - | T89: - | U89: - | V89: - | W89: - | X89: - | Y89: - | Z89: - | AA89: - | AB89: -
A90: =A89+1 -> 89 | B90: BAJO | C90: Pendiente | D90: AMARILLO | E90: =IF(OR($B90="ALTA",AND(ISNUMBER($W90),$W90>0),AND($U90<>"",$U90<>"NO")),"SI","") -> SI | F90: Comuna 19 | G90: Sur | H90: San Fernando | I90: Edificio | J90: calle 5b1 # 36b-06 | K90: Mantis | L90: =CONCATENATE(J90,", ",H90,", Cali") -> calle 5b1 # 36b-06, San Fernando, Cali | M90: Daño estructural, evacuación controlada | N90: Afectación estructural | T90: 1 | W90: 1 | Y90: Wilmar Valencia - Nicolas Quintero | Z90: Se reporta a fiscalia
A91: =A90+1 -> 90 | B91: BAJO | C91: En atención | D91: MORADO | E91: =IF(OR($B91="ALTA",AND(ISNUMBER($W91),$W91>0),AND($U91<>"",$U91<>"NO")),"SI","") | F91: Comuna 4 | G91: Norte | H91: Salomia | I91: Edificio | J91: Calle 48 #4D-11 | K91: Edificio Torres de Salomia | L91: =CONCATENATE(J91,", ",H91,", Cali") -> Calle 48 #4D-11, Salomia, Cali | M91: Daño estructural, evacuación controlada | N91: Afectación estructural | Q91: PROFESIONAL VOLUNTARIO | T91: 1
A92: =A91+1 -> 91 | B92: BAJO | C92: En atención | D92: MORADO | E92: =IF(OR($B92="ALTA",AND(ISNUMBER($W92),$W92>0),AND($U92<>"",$U92<>"NO")),"SI","") -> SI | F92: Comuna 18 | G92: Sur | H92: Buenos Aires | I92: Edificio | J92: Calle 3d con carrera 67 | L92: =CONCATENATE(J92,", ",H92,", Cali") -> Calle 3d con carrera 67, Buenos Aires, Cali | M92: Daño estructural, evacuación controlada | N92: Afectación estructural | Q92: PROFESIONAL VOLUNTARIO | T92: 1 | W92: 3
A93: =A92+1 -> 92 | B93: MEDIO | C93: En validación | D93: AMARILLO | E93: =IF(OR($B93="ALTA",AND(ISNUMBER($W93),$W93>0),AND($U93<>"",$U93<>"NO")),"SI","") -> SI | F93: Comuna 5 | G93: Norte | H93: Barranquilla | I93: Edificio | J93: Calle 56 # 3 -88 | L93: =CONCATENATE(J93,", ",H93,", Cali") -> Calle 56 # 3 -88, Barranquilla, Cali | M93: Daño estructural, evacuación controlada | N93: Afectación estructural | Q93: RIESGOS | T93: 1 | W93: 6 | Y93: Jose Apolinar | Z93: Secretaria de salud para certificado de defuncion
A94: =A93+1 -> 93 | B94: MEDIO | C94: Atendido | D94: AMARILLO | E94: =IF(OR($B94="ALTA",AND(ISNUMBER($W94),$W94>0),AND($U94<>"",$U94<>"NO")),"SI","") | F94: Comuna 19 | G94: Sur | H94: Cuarto de Legua | I94: Edificio | J94: Calle 1f carrera 59 | K94: Edificio Maria Josefa | L94: =CONCATENATE(J94,", ",H94,", Cali") -> Calle 1f carrera 59, Cuarto de Legua, Cali | M94: Daño estructural | N94: Afectación estructural | O94: SI | Q94: RIESGOS | T94: 1 | Y94: Carlos Rua | Z94: Evacuado por residentes
A95: =A94+1 -> 94 | B95: - | C95: ANULADO | D95: NARANJA | E95: - | F95: - | G95: - | H95: - | I95: - | J95: - | K95: - | L95: - | M95: - | N95: - | O95: - | P95: - | Q95: - | R95: - | T95: - | U95: - | V95: - | W95: - | X95: - | Y95: - | Z95: - | AA95: - | AB95: -
A96: =A95+1 -> 95 | B96: BAJO | C96: En atención | D96: MORADO | E96: =IF(OR($B96="ALTA",AND(ISNUMBER($W96),$W96>0),AND($U96<>"",$U96<>"NO")),"SI","") | F96: Comuna 3 | G96: Centro | H96: San Pedro | I96: Edificio | J96: Cra. 7 # 10-19 | K96: Unidad Residencial Las Palmas | L96: =CONCATENATE(J96,", ",H96,", Cali") -> Cra. 7 # 10-19, San Pedro, Cali | M96: Daño estructural, evacuación controlada | N96: Afectación estructural | Q96: PROFESIONAL VOLUNTARIO | T96: 1
A97: =A96+1 -> 96 | B97: BAJO | C97: En atención | D97: MORADO | E97: =IF(OR($B97="ALTA",AND(ISNUMBER($W97),$W97>0),AND($U97<>"",$U97<>"NO")),"SI","") | F97: Comuna 19 | G97: Sur | H97: El lido | I97: Casa | J97: Calle 4 con carrera 44 | L97: =CONCATENATE(J97,", ",H97,", Cali") -> Calle 4 con carrera 44, El lido, Cali | M97: Daño estructural, evacuación controlada | N97: Afectación estructural | Q97: PROFESIONAL VOLUNTARIO | T97: 1
A98: =A97+1 -> 97 | B98: BAJO | C98: En validación | D98: AMARILLO | E98: =IF(OR($B98="ALTA",AND(ISNUMBER($W98),$W98>0),AND($U98<>"",$U98<>"NO")),"SI","") | F98: Comuna 3 | G98: Centro | H98: San Pedro | I98: Edificio | J98: Carrera 7 con calle 12 | L98: =CONCATENATE(J98,", ",H98,", Cali") -> Carrera 7 con calle 12, San Pedro, Cali | M98: Daño estructural, evacuación controlada | N98: Afectación estructural | Q98: RIESGOS | T98: 1 | Y98: Carlos Rua | Z98: Verificar si hay personas atrapadas
A99: =A98+1 -> 98 | B99: ALTA | C99: En validación | D99: AMARILLO | E99: =IF(OR($B99="ALTA",AND(ISNUMBER($W99),$W99>0),AND($U99<>"",$U99<>"NO")),"SI","") -> SI | F99: Comuna 19 | G99: Sur | H99: San Fernando | I99: Casa | J99: Carrera 39/38A # 5d - 09 | L99: =CONCATENATE(J99,", ",H99,", Cali") -> Carrera 39/38A # 5d - 09, San Fernando, Cali | M99: Colapso Estructural | N99: Colapso Estructural | Q99: PAZ Y CULTURA | R99: 1 | U99: SI | Y99: Francisco Qesada y patricia de la pava | Z99: Colapso de infraestructura
A100: =A99+1 -> 99 | B100: BAJO | C100: En atención | D100: MORADO | E100: =IF(OR($B100="ALTA",AND(ISNUMBER($W100),$W100>0),AND($U100<>"",$U100<>"NO")),"SI","") -> SI | F100: Comuna 19 | G100: Sur | H100: San Fernando | I100: Edificio | J100: calle 36 # 5 - 145 | K100: Edificio - Torre Mantis | L100: =CONCATENATE(J100,", ",H100,", Cali") -> calle 36 # 5 - 145, San Fernando, Cali | M100: Colapso Estructural | N100: Colapso Estructural | Q100: PROFESIONAL VOLUNTARIO | R100: 1 | W100: 1 | Z100: Persona fallecida por caída de escombros, Pendiente del retiro del cuerpo
...

Sheet Tabla dinámica 10

Sheet Tabla dinámica 9

Sheet Datos5-Atendido
B1: Prioridad | C1: Estado | D1: Color semaforo | E1: Urgente | F1: Comuna - Corregimiento | G1: Sector | H1: Barrio | I1: Tipo | J1: Direccion | K1: Referencia | L1: Direccion completa | M1: Descripción | N1: Normalizacion | O1: Personas Evacuadas | P1: Seres sintientes | Q1: Atencion de la respuesta | R1: Colapso Total | S1: Colapso Parcial | T1: Daños | U1: Atrapamientos | V1: Rescatados | W1: Fallecidos | X1: Hospital/Clinica | Y1: NOMBRE DELEGADO | Z1: Observación Gestión del Riesgo | AA1: SOLICITUDES PENDIENTES | AB1: REFERENCIADO EN EL MAPA | AC1: DESAPARECIDOS | AD1: COORDENADAS
A2: 1 | B2: ALTA | C2: Atendido | D2: NARANJA | E2: SI | F2: Comuna 19 | G2: Sur | H2: El Lido | I2: Edificio | J2: Carrera 44 con calle 5 | L2: Carrera 44 con calle 5, El Lido, Cali | M2: Colapso de 3 edificaciones y 4 en riesgo de colapso | N2: Colapso Estructural | Q2: BROS - DCC | R2: 1 | U2: SI | V2: 7 | W2: 3 | Y2: DANIELA GONZALEZ/MAFE | Z2: En atención se requiere busqueda tecnica. (Bros).. Se asistio con 5 Recursos (máquinas y vehículo de comando), en horas de la noche nos retiramos. El área queda LIMPIA | AA2: Actualización BROS
A3: 12 | B3: BAJO | C3: Atendido | D3: VERDE | F3: Comuna 9 | G3: Centro | H3: Junin | I3: Edificio | J3: Autopista Sur # 13-01 | K3: Hotel La Luna | L3: Autopista Sur # 13-01, Junin, Cali | M3: Colapso estructural | N3: Colapso Estructural | Q3: CRC | R3: 1 | U3: NO | Y3: Giovanny Ordoñez y Felipe Galves | Z3: Se cayo el hotel la luna, no hay personas atrapadas. (Bros)... No hubo intervención por parte de Bomberos
A4: 23 | B4: BAJO | C4: Atendido | D4: VERDE | E4: SI | F4: Comuna 19 | G4: Sur | H4: El Lido | I4: Casa | J4: Carrera 52 # 3 20 | K4: Bodega de reciclaje | L4: Carrera 52 # 3 20 , El Lido, Cali | M4: Colapso estructural | N4: Colapso Estructural | O4: SI | Q4: BROS | R4: 1 | U4: NO | W4: 2 | Z4: Atendido, sin personas atrapadas
A5: 83 | B5: MEDIO | C5: Atendido | D5: VERDE | F5: Comuna 19 | G5: Sur | H5: San Fernando | I5: Edificio | J5: Carrera 37 # 5b1 - 37 | K5: Edificio Liliana | L5: Carrera 37 # 5b1 - 37 , San Fernando, Cali | M5: Colapso estructural | N5: Colapso estructural | O5: SI | R5: 1 | Z5: Edificio de 4 pisos con colapso total 10 apartamentos

Sheet Datos4-En validación -Colapso E
B1: Prioridad | C1: Estado | D1: Color semaforo | E1: Urgente | F1: Comuna - Corregimiento | G1: Sector | H1: Barrio | I1: Tipo | J1: Direccion | K1: Referencia | L1: Direccion completa | M1: Descripción | N1: Normalizacion | O1: Personas Evacuadas | P1: Seres sintientes | Q1: Atencion de la respuesta | R1: Colapso Total | S1: Colapso Parcial | T1: Daños | U1: Atrapamientos | V1: Rescatados | W1: Fallecidos | X1: Hospital/Clinica | Y1: NOMBRE DELEGADO | Z1: Observación Gestión del Riesgo | AA1: SOLICITUDES PENDIENTES | AB1: REFERENCIADO EN EL MAPA | AC1: DESAPARECIDOS
A2: 98 | B2: ALTA | C2: En validación | D2: AMARILLO | E2: SI | F2: Comuna 19 | G2: Sur | H2: San Fernando | I2: Casa | J2: Carrera 39/38A # 5d - 09 | L2: Carrera 39/38A # 5d - 09, San Fernando, Cali | M2: Colapso Estructural | N2: Colapso Estructural | Q2: PAZ Y CULTURA | R2: 1 | U2: SI | Y2: Francisco Qesada y patricia de la pava | Z2: Colapso de infraestructura
A3: 113 | B3: MEDIO | C3: En validación | D3: AMARILLO | F3: Comuna 18 | G3: Sur | H3: Alto Jordan | I3: Edificio | J3: Carrera 94d # calle 2 a bis - entre carreras 94c1 y 94b1 | L3: Carrera 94d # calle 2 a bis - entre carreras 94c1 y 94b1, Alto Jordan , Cali | M3: Colapso estructural | N3: Colapso Estructural | Q3: EDRU | R3: 1 | Y3: Carolina Soto - Juan Cralos

Sheet Datos3-Atendido-Colapso Estruct
B1: Prioridad | C1: Estado | D1: Color semaforo | E1: Urgente | F1: Comuna - Corregimiento | G1: Sector | H1: Barrio | I1: Tipo | J1: Direccion | K1: Referencia | L1: Direccion completa | M1: Descripción | N1: Normalizacion | O1: Personas Evacuadas | P1: Seres sintientes | Q1: Atencion de la respuesta | R1: Colapso Total | S1: Colapso Parcial | T1: Daños | U1: Atrapamientos | V1: Rescatados | W1: Fallecidos | X1: Hospital/Clinica | Y1: NOMBRE DELEGADO | Z1: Observación Gestión del Riesgo | AA1: SOLICITUDES PENDIENTES | AB1: REFERENCIADO EN EL MAPA | AC1: DESAPARECIDOS
A2: 1 | B2: ALTA | C2: Atendido | D2: NARANJA | E2: SI | F2: Comuna 19 | G2: Sur | H2: El Lido | I2: Edificio | J2: Carrera 44 con calle 5 | L2: Carrera 44 con calle 5, El Lido, Cali | M2: Colapso de 3 edificaciones y 4 en riesgo de colapso | N2: Colapso Estructural | Q2: BROS - DCC | R2: 1 | U2: SI | V2: 7 | W2: 3 | Y2: DANIELA GONZALEZ/MAFE | Z2: En atención se requiere busqueda tecnica. (Bros).. Se asistio con 5 Recursos (máquinas y vehículo de comando), en horas de la noche nos retiramos. El área queda LIMPIA | AA2: Actualización BROS
A3: 12 | B3: BAJO | C3: Atendido | D3: VERDE | F3: Comuna 9 | G3: Centro | H3: Junin | I3: Edificio | J3: Autopista Sur # 13-01 | K3: Hotel La Luna | L3: Autopista Sur # 13-01, Junin, Cali | M3: Colapso estructural | N3: Colapso Estructural | Q3: CRC | R3: 1 | U3: NO | Y3: Giovanny Ordoñez y Felipe Galves | Z3: Se cayo el hotel la luna, no hay personas atrapadas. (Bros)... No hubo intervención por parte de Bomberos
A4: 23 | B4: BAJO | C4: Atendido | D4: VERDE | E4: SI | F4: Comuna 19 | G4: Sur | H4: El Lido | I4: Casa | J4: Carrera 52 # 3 20 | K4: Bodega de reciclaje | L4: Carrera 52 # 3 20 , El Lido, Cali | M4: Colapso estructural | N4: Colapso Estructural | O4: SI | Q4: BROS | R4: 1 | U4: NO | W4: 2 | Z4: Atendido, sin personas atrapadas

Sheet 901
A1: LA FLORA | B1: AVENIDA 6A CON 35 NOTARIA QUINTA | C1: 1 ADULTO | D1: MASCULINO | E1: 1
A2: LA FLORA | B2: CLL 7 CON 21 | C2: 1 ADULTO | D2: FEMENINO | E2: 1
A3: LIDO | B3: CR 56 d3-150B CUARTO DE LEGUA | C3: 3 FALLECIDOS MUJERES | D3: FEMENINA | E3: 3
A4: LIMONAR | B4: CRA 98B-48 127 EDIFICIO RESIDENCIAL SANTA ANA | C4: 01 FALLECIDO | D4: MASCULINO | E4: 1
A5: GUABAL | B5: CALLE 13 CON CARRERA 43A | C5: 01 FALLECIDO | D5: FEMENINA | E5: 1
A6: MELENDEZ | B6: GRAN COLOMBIA 70 CON 2 | C6: 01 FALLECIDA 18 AñOS | D6: FEMENINA | E6: 1
A7: LIMONAR | B7: CRA 98B -48-127 | C7: 01 FALLECIDA | D7: FEMENINA | E7: 1
A8: LIMONAR | B8: CRA 72 CON 10-42 | C8: 02 FALLECIDA | D8: FEMENINA | E8: 2
A9: LIDO | B9: CL 5 CR 5b PAMPALINA | C9: 4 £EMININA5 Y 1 MASCULINO MAYORES DE EDAD | D9: M/£ | E9: 5
A10: LIDO | B10: cr 36a 5-145 b/ san fernanddo | C10: 01 MAYOR | D10: MASCULINO | E10: 1
A11: LIDO | B11: cl 5b2 38a-50 b/ san fernando | C11: 02 MAYOR | D11: MASCULINO | E11: 2
A12: LIDO | B12: cl 5a 43•5d b/ tequendama | C12: 02 MAYOR | D12: MAF | E12: 2
... A30: LIDO | B30: CL 3 CR 57 | C30: EUA VALENCIA 84 ANOS | D30: | FEMENINA | E30: 1
E31: =SUM(E1:E30) -> 47

Sheet Copia de Hoja2
A1: RECURSOS DE APOYO | B1: TRANSITO | C1: SGRD | D1: BROS | E1: DCC | F1: CRC
A3: BIADE | B3: 30
A4: Accesibilidad y transporte | C4: palmeto, utompista con 70 y notaria 20
A5: USAR | D5: POPAYAN TULUA PALMIRA BUGA YUMBO VILLA RICA | E5: X | F5: X
A6: Energia GAS
A7: Ingenieros estructurales | B7: Poliica Metropolitana Calle 41 norte 4 N 170 norte Carrera 56 calle 4 y calle 3

Sheet CAPACIADES 
B1: USAR MEIDANO | C1: CANINOS | D1: USAR LIBIA | E1: PERSONAL | F1: VEHICULOS | G1: CAMION | H1: Retro | I1: Minicargadores | J1: Volquetas | K1: Evaluacion estructuras | L1: Internet satelital
A2: BROS CALI | B2: 1 | E2: 260 | F2: 20
A3: BORS YUMBO | D3: 1 | E3: 15 | F3: 2
A4: POPAYAN | D4: 1 | E4: 15 | F4: 3
A5: VILLARICA | D5: 1 | E5: 15 | F5: 3
A6: JAMUNDI | D6: 1 | E6: 15 | F6: 2
A7: PALMIRA | D7: 1 | E7: 15 | F7: 2
A8: BOGOTA | D8: 1 | E8: 60
A9: CRC | E9: 102 | F9: 3
A10: SGRED | E10: 50 | F10: 4
A11: POLICIA | E11: 180
A12: INFRA | F12: 2
A13: DCC CALI | E13: 200 | F13: 4
A14: DCC-BOYACA | D14: 1 | E14: 15
A15: DCC-SANTANDER | D15: 1 | E15: 15
A16: DCC- NARIÑO | E16: 19
A17: MOVILDAD | E17: 250
A18: UAESP
A19: INFRAESTRUCTURA | E19: 20
A20: BIADE | B20: 1 | C20: 1 | E20: 55
A21: PASTO | B21: 1 | E21: 22
A22: PONALSAR | B22: 1 | C22: 2 | E22: 14
A23: ARMADA | B23: 1 | E23: 30
A24: METROCALI | E24: 20 | L24: 3
A25: SUESCA | E25: 5
E26: =SUM(E2:E25) -> 1392
A29: Diana Romero | B29: SUESCA | C29: 3192338267 | D29: 5 PERSONAS
